structuregraph_helpers/__init__.py
structuregraph_helpers/_hasher.py
structuregraph_helpers/analysis.py
structuregraph_helpers/cli.py
structuregraph_helpers/create.py
structuregraph_helpers/delete.py
structuregraph_helpers/hash.py
structuregraph_helpers/plotting.py
structuregraph_helpers/subgraph.py
structuregraph_helpers/utils.py
structuregraph_helpers/version.py
structuregraph_helpers/data/atom_typing_radii.yml
structuregraph_helpers/data/li_radii.yml
structuregraph_helpers/data/tuned_vesta.yml
structuregraph_helpers-0.0.9.dist-info/LICENSE
structuregraph_helpers-0.0.9.dist-info/METADATA
structuregraph_helpers-0.0.9.dist-info/WHEEL
structuregraph_helpers-0.0.9.dist-info/entry_points.txt
structuregraph_helpers-0.0.9.dist-info/top_level.txt
structuregraph_helpers-0.0.9.dist-info/RECORD
