Metadata-Version: 2.1
Name: structuregraph-helpers
Version: 0.0.9
Summary: Utilities for working with structure graphs
Home-page: https://github.com/kjappelbaum/structuregraph-helpers
Download-URL: https://github.com/kjappelbaum/structuregraph-helpers/releases
Author: Kevin M. Jablonka
Author-email: mail@kjablonka.com
Maintainer: Kevin M. Jablonka
Maintainer-email: mail@kjablonka.com
License: MIT
Project-URL: Bug Tracker, https://github.com/kjappelbaum/structuregraph-helpers/issues
Project-URL: Source Code, https://github.com/kjappelbaum/structuregraph-helpers
Keywords: materials,pymatgen,structuregraph,graph,crystallography
Classifier: Development Status :: 1 - Planning
Classifier: Environment :: Console
Classifier: Intended Audience :: Developers
Classifier: License :: OSI Approved :: MIT License
Classifier: Operating System :: OS Independent
Classifier: Framework :: Pytest
Classifier: Framework :: tox
Classifier: Framework :: Sphinx
Classifier: Programming Language :: Python
Classifier: Programming Language :: Python :: 3.7
Classifier: Programming Language :: Python :: 3.8
Classifier: Programming Language :: Python :: 3.9
Classifier: Programming Language :: Python :: 3.10
Classifier: Programming Language :: Python :: 3 :: Only
Requires-Python: >=3.7
License-File: LICENSE
Requires-Dist: pymatgen
Requires-Dist: pyyaml
Requires-Dist: loguru
Requires-Dist: click
Provides-Extra: docs
Requires-Dist: sphinx ; extra == 'docs'
Requires-Dist: sphinx-book-theme ; extra == 'docs'
Requires-Dist: sphinx-click ; extra == 'docs'
Requires-Dist: sphinx-autodoc-typehints ; extra == 'docs'
Requires-Dist: sphinx-automodapi ; extra == 'docs'
Requires-Dist: sphinx-copybutton ; extra == 'docs'
Provides-Extra: lint
Requires-Dist: isort ; extra == 'lint'
Requires-Dist: black ; extra == 'lint'
Requires-Dist: flake8 ; extra == 'lint'
Requires-Dist: pre-commit ; extra == 'lint'
Requires-Dist: bumpversion ; extra == 'lint'
Provides-Extra: plotting
Requires-Dist: plotly ; extra == 'plotting'
Provides-Extra: tests
Requires-Dist: pytest ; extra == 'tests'
Requires-Dist: tox ; extra == 'tests'
Requires-Dist: coverage ; extra == 'tests'
